fluent_assertions/__init__.py
fluent_assertions-0.1.4.dist-info/METADATA
fluent_assertions-0.1.4.dist-info/WHEEL
fluent_assertions-0.1.4.dist-info/licenses/LICENSE
fluent_assertions-0.1.4.dist-info/RECORD
