Metadata-Version: 2.3
Name: fluent-assertions
Version: 0.1.4
Summary: Fluent API for assertions supporting pytest with focus on developer experience.
Project-URL: Repository, https://github.com/VictorKuenstler/fluent-assertions.git
Project-URL: Issues, https://github.com/VictorKuenstler/fluent-assertions/issues
Project-URL: Documentation, https://victorkuenstler.github.io/fluent-assertions/fluent_assertions.html
Author: Victor Künstler
License: MIT License
License-File: LICENSE
Keywords: assertions,fluent,fluent assertions,fluentAPI,pytest,testing,typing
Classifier: Development Status :: 3 - Alpha
Classifier: Intended Audience :: Developers
Classifier: License :: OSI Approved :: MIT License
Classifier: Programming Language :: Python :: 3.12
Classifier: Topic :: Software Development :: Testing
Requires-Python: >=3.12
Requires-Dist: pytest>=7.0.0
